brdata/__init__.py
brdata/core/__init__.py
brdata/core/crawler.py
brdata/core/exceptions.py
brdata/core/req.py
brdata/crawlers/__init__.py
brdata/crawlers/cvm.py
brdata/crawlers/valor.py
brdata/crawlers/xpi.py
brasil_data-1.0.1.dist-info/LICENSE
brasil_data-1.0.1.dist-info/METADATA
brasil_data-1.0.1.dist-info/WHEEL
brasil_data-1.0.1.dist-info/RECORD
