Metadata-Version: 2.1
Name: brasil-data
Version: 1.0.1
Summary: Brazilian financial market data sources
Home-page: https://github.com/gabrielguarisa/brdata
License: MIT
Keywords: data,dados,brasil,br,brazil,finance,financeiro,mercado
Author: Gabriel Guarisa
Author-email: gabrielguarisa@gmail.com
Requires-Python: >=3.9,<3.13
Classifier: License :: OSI Approved :: MIT License
Classifier: Programming Language :: Python :: 3
Classifier: Programming Language :: Python :: 3.9
Classifier: Programming Language :: Python :: 3.10
Classifier: Programming Language :: Python :: 3.11
Requires-Dist: beautifulsoup4 (>=4.11.2)
Requires-Dist: cache-decorator (>=2.1.15,<3.0.0)
Requires-Dist: html5lib (>=1.1)
Requires-Dist: pandas (>=1.5.3)
Requires-Dist: random-user-agent (>=1.0.1,<2.0.0)
Requires-Dist: requests (>=2.31.0)
Project-URL: Repository, https://github.com/gabrielguarisa/brdata
